jsonversation/__init__.py
jsonversation/py.typed
jsonversation/aio/__init__.py
jsonversation/aio/models.py
jsonversation/aio/parser.py
jsonversation/sync/__init__.py
jsonversation/sync/models.py
jsonversation/sync/parser.py
jsonversation/sync/py.typed
jsonversation-0.1.3.dist-info/licenses/LICENSE
jsonversation-0.1.3.dist-info/METADATA
jsonversation-0.1.3.dist-info/WHEEL
jsonversation-0.1.3.dist-info/top_level.txt
jsonversation-0.1.3.dist-info/RECORD
