Metadata-Version: 2.4
Name: jsonversation
Version: 0.1.3
Summary: Fast and type-safe JSON stream parser
Author-email: "Vetted.ai Engineering" <engineering@vetted.ai>
Requires-Python: >=3.13
License-File: LICENSE
Requires-Dist: jiter>=0.10.0
Requires-Dist: pydantic>=2.11.7
Requires-Dist: pytest-asyncio>=1.1.0
Dynamic: license-file
